LICENSE.rst
MANIFEST.in
README.rst
setup.cfg
setup.py
cpp/Lame.cpp
cpp/PyHeader.hpp
cpp/lib/AIFFFile.cpp
cpp/lib/AIFFFile.hpp
cpp/lib/Conversions.cpp
cpp/lib/Conversions.hpp
cpp/lib/DataChunk.cpp
cpp/lib/DataChunk.hpp
cpp/lib/Form.cpp
cpp/lib/Form.hpp
cpp/lib/Iterator32.cpp
cpp/lib/Iterator32.hpp
cpp/lib/MP3Encoder.cpp
cpp/lib/MP3Encoder.hpp
cpp/lib/PCMData.cpp
cpp/lib/PCMData.hpp
cpp/lib/PCMFile.cpp
cpp/lib/PCMFile.hpp
cpp/lib/WAVFile.cpp
cpp/lib/WAVFile.hpp
cpp/lib/base.cpp
cpp/lib/base.hpp
cpp/lib/lamer.hpp
cpp/lib/main.cpp
cpp/lib/transcoder.cpp
cpp/lib/transcoder.hpp
pcm2mp3.egg-info/PKG-INFO
pcm2mp3.egg-info/SOURCES.txt
pcm2mp3.egg-info/dependency_links.txt
pcm2mp3.egg-info/top_level.txt
pcm2mp3.egg-info/zip-safe
tests/__init__.py
tests/time.py
utils/__init__.py
utils/checkForLibs.py
utils/clean.py