Metadata-Version: 1.1
Name: pcm2mp3
Version: 1.8
Summary: Utility to convert PCM files to MP3 files
Home-page: https://github.com/jdstmporter/pcm2mp3.git
Author: Julian Porter
Author-email: julian@jpembedded.solution
License: BSD 3-Clause License
